conf/__init__.py
punctuation/__init__.py
punctuation/config.py
punctuation/consistency/__init__.py
punctuation/consistency/consistency_computation.py
punctuation/consistency/consistency_shw.py
punctuation/consistency/consistency_visualisation.py
punctuation/feature_operations/__init__.py
punctuation/feature_operations/distance_matrices.py
punctuation/feature_operations/distances.py
punctuation/feature_operations/matrix_operations.py
punctuation/parser/__init__.py
punctuation/parser/digilibraries_parser.py
punctuation/parser/gutenberg_cache_parser.py
punctuation/parser/gutenberg_parser.py
punctuation/parser/punctuation_parser.py
punctuation/recognition/__init__.py
punctuation/recognition/recognition_algorithms.py
punctuation/recognition/training_testing_split.py
punctuation/time_series/__init__.py
punctuation/time_series/time_functions.py
punctuation/utils/__init__.py
punctuation/utils/convert_epub2text.py
punctuation/utils/utils.py
punctuation/visualisation/__init__.py
punctuation/visualisation/heatmap_functions.py
punctuation/visualisation/heatmap_rawdata.py
punctuation/visualisation/visualisation.py
results/__init__.py
tests/__init__.py
punctuation_stylometry-0.0.11.dist-info/LICENSE
punctuation_stylometry-0.0.11.dist-info/METADATA
punctuation_stylometry-0.0.11.dist-info/WHEEL
punctuation_stylometry-0.0.11.dist-info/dependency_links.txt
punctuation_stylometry-0.0.11.dist-info/top_level.txt
punctuation_stylometry-0.0.11.dist-info/RECORD
