Metadata-Version: 2.1
Name: punctuation-stylometry
Version: 0.0.11
Summary: This package represents the code used for the publication of the article  https://arxiv.org/abs/1901.00519
Home-page: https://github.com/alex-darmon/punctuation-stylometry
Author: alexdarmon
Author-email: alexandra.darmon@hotmail.fr
License: UNKNOWN
Platform: UNKNOWN
Classifier: Programming Language :: Python :: 3
Classifier: License :: OSI Approved :: MIT License
Classifier: Operating System :: OS Independent
Requires-Python: >=3.6
Requires-Dist: alabaster (==0.7.12)
Requires-Dist: alembic (==1.0.11)
Requires-Dist: appnope (==0.1.0)
Requires-Dist: asn1crypto (==0.24.0)
Requires-Dist: astroid (==2.2.5)
Requires-Dist: attrs (==19.1.0)
Requires-Dist: Babel (==2.7.0)
Requires-Dist: backcall (==0.1.0)
Requires-Dist: base58 (==2.0.0)
Requires-Dist: bleach (==3.1.0)
Requires-Dist: blis (==0.2.4)
Requires-Dist: bsddb3 (==6.2.6)
Requires-Dist: bz2file (==0.98)
Requires-Dist: cbor2 (==4.1.2)
Requires-Dist: certifi (==2019.6.16)
Requires-Dist: cffi (==1.12.3)
Requires-Dist: chardet (==3.0.4)
Requires-Dist: cloudpickle (==1.2.1)
Requires-Dist: ConfigArgParse (==0.14.0)
Requires-Dist: coverage (==5.1)
Requires-Dist: cryptography (==2.7)
Requires-Dist: cycler (==0.10.0)
Requires-Dist: cymem (==2.0.2)
Requires-Dist: dataclasses (==0.6)
Requires-Dist: decorator (==4.4.0)
Requires-Dist: defusedxml (==0.6.0)
Requires-Dist: EbookLib (==0.17.1)
Requires-Dist: ecdsa (==0.15)
Requires-Dist: entrypoints (==0.3)
Requires-Dist: epub (==0.5.2)
Requires-Dist: epub-conversion (==1.0.7)
Requires-Dist: frozendict (==1.2)
Requires-Dist: future (==0.17.1)
Requires-Dist: gitdb (==4.0.4)
Requires-Dist: GitPython (==3.1.1)
Requires-Dist: Gutenberg (==0.7.0)
Requires-Dist: html2text (==2019.8.11)
Requires-Dist: idna (==2.8)
Requires-Dist: ifaddr (==0.1.6)
Requires-Dist: imagesize (==1.1.0)
Requires-Dist: importlib-metadata (==1.3.0)
Requires-Dist: ipykernel (==5.1.1)
Requires-Dist: ipython (==7.7.0)
Requires-Dist: ipython-genutils (==0.2.0)
Requires-Dist: ipywidgets (==7.5.1)
Requires-Dist: isodate (==0.6.0)
Requires-Dist: isort (==4.3.21)
Requires-Dist: jedi (==0.13.3)
Requires-Dist: joblib (==0.13.2)
Requires-Dist: jsonschema (==3.0.1)
Requires-Dist: jupyter (==1.0.0)
Requires-Dist: jupyter-client (==5.3.1)
Requires-Dist: jupyter-console (==6.0.0)
Requires-Dist: jupyter-core (==4.5.0)
Requires-Dist: keyring (==18.0.0)
Requires-Dist: kiwisolver (==1.1.0)
Requires-Dist: lazy-object-proxy (==1.4.1)
Requires-Dist: lxml (==4.4.1)
Requires-Dist: Mako (==1.1.0)
Requires-Dist: MarkupSafe (==1.1.1)
Requires-Dist: matplotlib (==3.1.1)
Requires-Dist: mccabe (==0.6.1)
Requires-Dist: mistune (==0.8.4)
Requires-Dist: more-itertools (==8.0.2)
Requires-Dist: murmurhash (==1.0.2)
Requires-Dist: mypy-extensions (==0.4.3)
Requires-Dist: nbconvert (==5.5.0)
Requires-Dist: nbformat (==4.4.0)
Requires-Dist: notebook (==6.0.0)
Requires-Dist: numpy (==1.16.4)
Requires-Dist: numpydoc (==0.9.1)
Requires-Dist: oyaml (==0.9)
Requires-Dist: packaging (==19.0)
Requires-Dist: pandas (==0.25.0)
Requires-Dist: pandocfilters (==1.4.2)
Requires-Dist: parso (==0.5.0)
Requires-Dist: patsy (==0.5.1)
Requires-Dist: pexpect (==4.7.0)
Requires-Dist: pickleshare (==0.7.5)
Requires-Dist: Pillow (==6.1.0)
Requires-Dist: pkginfo (==1.5.0.1)
Requires-Dist: plac (==0.9.6)
Requires-Dist: preshed (==2.0.1)
Requires-Dist: prometheus-client (==0.7.1)
Requires-Dist: prompt-toolkit (==2.0.9)
Requires-Dist: psutil (==5.6.3)
Requires-Dist: ptyprocess (==0.6.0)
Requires-Dist: pybase64 (==1.0.1)
Requires-Dist: pycodestyle (==2.5.0)
Requires-Dist: pycparser (==2.19)
Requires-Dist: pyflakes (==2.1.1)
Requires-Dist: Pygments (==2.4.2)
Requires-Dist: pylatexenc (==2.1)
Requires-Dist: pylint (==2.3.1)
Requires-Dist: pyOpenSSL (==19.0.0)
Requires-Dist: pyparsing (==2.4.0)
Requires-Dist: pyrsistent (==0.14.11)
Requires-Dist: PySocks (==1.7.0)
Requires-Dist: python-dateutil (==2.8.0)
Requires-Dist: python-editor (==1.0.4)
Requires-Dist: pytz (==2019.1)
Requires-Dist: pyzmq (==18.0.0)
Requires-Dist: QtAwesome (==0.5.7)
Requires-Dist: qtconsole (==4.5.2)
Requires-Dist: QtPy (==1.8.0)
Requires-Dist: rdflib (==4.2.2)
Requires-Dist: rdflib-sqlalchemy (==0.3.8)
Requires-Dist: readme-renderer (==24.0)
Requires-Dist: requests (==2.22.0)
Requires-Dist: requests-toolbelt (==0.9.1)
Requires-Dist: rope (==0.14.0)
Requires-Dist: scikit-learn (==0.21.3)
Requires-Dist: scipy (==1.3.1)
Requires-Dist: seaborn (==0.9.0)
Requires-Dist: Send2Trash (==1.5.0)
Requires-Dist: six (==1.12.0)
Requires-Dist: sklearn (==0.0)
Requires-Dist: smmap (==3.0.2)
Requires-Dist: snowballstemmer (==1.9.0)
Requires-Dist: spacy (==2.1.8)
Requires-Dist: Sphinx (==2.1.2)
Requires-Dist: sphinxcontrib-applehelp (==1.0.1)
Requires-Dist: sphinxcontrib-devhelp (==1.0.1)
Requires-Dist: sphinxcontrib-htmlhelp (==1.0.2)
Requires-Dist: sphinxcontrib-jsmath (==1.0.1)
Requires-Dist: sphinxcontrib-qthelp (==1.0.2)
Requires-Dist: sphinxcontrib-serializinghtml (==1.1.3)
Requires-Dist: spyder (==3.3.6)
Requires-Dist: spyder-kernels (==0.5.1)
Requires-Dist: srsly (==0.0.7)
Requires-Dist: statsmodels (==0.10.2)
Requires-Dist: termcolor (==1.1.0)
Requires-Dist: terminado (==0.8.2)
Requires-Dist: testpath (==0.4.2)
Requires-Dist: texttable (==1.6.2)
Requires-Dist: thinc (==7.0.8)
Requires-Dist: timeout-decorator (==0.4.1)
Requires-Dist: tornado (==6.0.3)
Requires-Dist: tqdm (==4.33.0)
Requires-Dist: traitlets (==4.3.2)
Requires-Dist: twine (==3.1.1)
Requires-Dist: typing-extensions (==3.7.4.2)
Requires-Dist: urllib3 (==1.24.2)
Requires-Dist: validate-email (==1.3)
Requires-Dist: wasabi (==0.2.2)
Requires-Dist: wcwidth (==0.1.7)
Requires-Dist: webcolors (==1.9.1)
Requires-Dist: webencodings (==0.5.1)
Requires-Dist: websocket-client (==0.57.0)
Requires-Dist: whichcraft (==0.6.1)
Requires-Dist: widgetsnbextension (==3.5.0)
Requires-Dist: wget (==3.2)
Requires-Dist: wrapt (==1.11.2)
Requires-Dist: wurlitzer (==1.0.3)
Requires-Dist: xml-cleaner (==2.0.4)
Requires-Dist: xtermcolor (==1.3)
Requires-Dist: zeroconf (==0.25.1)
Requires-Dist: zipp (==0.6.0)
Requires-Dist: zuper-commons-z5 (==5.0.11)
Requires-Dist: zuper-ipce-z5 (==5.3.0)
Requires-Dist: zuper-typing-z5 (==5.3.0)
